core/__init__.py
core/logic.py
verso-0.1.2.data/scripts/verso
verso-0.1.2.dist-info/LICENSE.txt
verso-0.1.2.dist-info/METADATA
verso-0.1.2.dist-info/WHEEL
verso-0.1.2.dist-info/top_level.txt
verso-0.1.2.dist-info/RECORD
