Metadata-Version: 2.1
Name: verso
Version: 0.1.2
Summary: Verso provides functionality for managing versioning
Home-page: https://github.com/tfagerlind/verso
Maintainer: Tomas Fägerlind
Maintainer-email: tomas.fagerlind@sofengi.com
License: MIT
Platform: UNKNOWN
Classifier: Programming Language :: Python :: 3
Classifier: License :: OSI Approved :: MIT License
Classifier: Operating System :: OS Independent
License-File: LICENSE.txt
Requires-Dist: click <9
Requires-Dist: semver <4,>=3
Requires-Dist: gitpython <4
